{
    "goleadores": [
        {"nombre": "Ariel Narváez (7)", "equipo": "SAN JOSÉ", "goles": 6},
        {"nombre": "Oscar Lucero (16)", "equipo": "SAN JOSÉ", "goles": 2},
        {"nombre": "Estiven Rodríguez (10)", "equipo": "SAN JOSÉ", "goles": 1},
        {"nombre": "Alexao Narváez (37)", "equipo": "SAN JOSÉ", "goles": 6},
        {"nombre": "Ever Narváez (35)", "equipo": "SAN JOSÉ", "goles": 1},
        {"nombre": "Gandhy Narváez (9)", "equipo": "SAN JOSÉ", "goles": 2},
        {"nombre": "Anderson Delgado (6)", "equipo": "SAN JOSÉ", "goles": 4},
        {"nombre": "Dennis Robles (110)", "equipo": "SAN JOSÉ", "goles": 1},
        {"nombre": "Galo Robles (56)", "equipo": "SAN JOSÉ", "goles": 1},
        {"nombre": "Elvis Narváez (77)", "equipo": "SAN JOSÉ", "goles": 2},
        {"nombre": "Hernando Yaguapaz (2)", "equipo": "SAN JOSÉ", "goles": 1},
        {"nombre": "Rony Quelal (25)", "equipo": "ÁGUILAS DEL PALMAR", "goles": 1},
        {"nombre": "Jordy Hurtado (28)", "equipo": "ÁGUILAS DEL PALMAR", "goles": 6},
        {"nombre": "Maykel Villota (8)", "equipo": "ÁGUILAS DEL PALMAR", "goles": 6},
        {"nombre": "Eduardo Armas (7)", "equipo": "ÁGUILAS DEL PALMAR", "goles": 1},
        {"nombre": "Andy Armas (20)", "equipo": "ÁGUILAS DEL PALMAR", "goles": 3},
        {"nombre": "Oscar Armas (18)", "equipo": "ÁGUILAS DEL PALMAR", "goles": 3},
        {"nombre": "Diego Cuamacás (14)", "equipo": "ÁGUILAS DEL PALMAR", "goles": 11},
        {"nombre": "William Matango (11)", "equipo": "ATLÉTICO S.F", "goles": 5},
        {"nombre": "José Chachalo (99)", "equipo": "ATLÉTICO S.F", "goles": 8},
        {"nombre": "Steven Matango (30)", "equipo": "ATLÉTICO S.F", "goles": 1},
        {"nombre": "Frankely Castro (10)", "equipo": "ATLÉTICO S.F", "goles": 1},
        {"nombre": "Jairo Criban (22)", "equipo": "ATLÉTICO S.F", "goles": 1},
        {"nombre": "Nicolas Pilca (13)", "equipo": "ATLÉTICO S.F", "goles": 1},
        {"nombre": "Javier Chachalo (19)", "equipo": "ATLÉTICO S.F", "goles": 5},
        {"nombre": "Bryan Lanchimba (3)", "equipo": "ATLÉTICO S.F", "goles": 6},
        {"nombre": "Gabriel Anrango (16)", "equipo": "ATLÉTICO S.F", "goles": 4},
        {"nombre": "Edwin Chachalo (33)", "equipo": "ATLÉTICO S.F", "goles": 7},
        {"nombre": "Santiago Pastas (94)", "equipo": "ATLÉTICO S.F", "goles": 2},
        {"nombre": "Gustavo Tulcán (4)", "equipo": "ATLÉTICO S.F", "goles": 2},
        {"nombre": "Andres Mafla (20)", "equipo": "LOS CAPOS", "goles": 3},
        {"nombre": "Nixon Mejia (11)", "equipo": "LOS CAPOS", "goles": 2},
        {"nombre": "Roni Suarez (31)", "equipo": "LOS CAPOS", "goles": 3},
        {"nombre": "Diego Castro (23)", "equipo": "LOS CAPOS", "goles": 4},
        {"nombre": "Genaro Mejia (10)", "equipo": "LOS CAPOS", "goles": 2},
        {"nombre": "Bryan Villota (66)", "equipo": "LOS CAPOS", "goles": 2},
        {"nombre": "Darlin Ortega (19)", "equipo": "LOS CAPOS", "goles": 1},
        {"nombre": "Eder Minda (51)", "equipo": "LOS CAPOS", "goles": 1},
        {"nombre": "Esteban Castro (22)", "equipo": "LOS CAPOS", "goles": 3},
        {"nombre": "Patrick Ichau (50)", "equipo": "LOS CAPOS", "goles": 6},
        {"nombre": "Jeferson Carapaz (14)", "equipo": "LOS CAPOS", "goles": 1},
        {"nombre": "Dario Bolaños (21)", "equipo": "LOS CAPOS", "goles": 1},
        {"nombre": "José Inbacuan (66)", "equipo": "IDEPENDIENTE S.R", "goles": 2},
        {"nombre": "Jeferson Terán (7)", "equipo": "IDEPENDIENTE S.R", "goles": 8},
        {"nombre": "Edgar Cabezas (3)", "equipo": "IDEPENDIENTE S.R", "goles": 1},
        {"nombre": "Ariel Aldas (17)", "equipo": "IDEPENDIENTE S.R", "goles": 2},
        {"nombre": "José Ulcuango (12)", "equipo": "IDEPENDIENTE S.R", "goles": 1},
        {"nombre": "Nicolas Aguirre (30)", "equipo": "IDEPENDIENTE S.R", "goles": 1},
        {"nombre": "Israel Quelal (19)", "equipo": "IDEPENDIENTE S.R", "goles": 1},
        {"nombre": "Winsten Bastidas", "equipo": "IDEPENDIENTE S.R", "goles": 1},
        {"nombre": "David Garces (10)", "equipo": "IDEPENDIENTE S.R", "goles": 15},
        {"nombre": "Mateo G. (8)", "equipo": "IDEPENDIENTE S.R", "goles": 3},
        {"nombre": "Michael Carapaz (99)", "equipo": "IDEPENDIENTE S.R", "goles": 6},
        {"nombre": "Dario Armas (5)", "equipo": "IDEPENDIENTE S.R", "goles": 1},
        {"nombre": "Daniel Jaramillo (24)", "equipo": "4 DKADAS", "goles": 5},
        {"nombre": "Fabricio Guapaz (23)", "equipo": "4 DKADAS", "goles": 3},
        {"nombre": "Alonso Carvajal", "equipo": "4 DKADAS", "goles": 2},
        {"nombre": "Estefano Benalcázar (8)", "equipo": "4 DKADAS", "goles": 2},
        {"nombre": "Michael Villota (25)", "equipo": "4 DKADAS", "goles": 4},
        {"nombre": "Paúl Carvajal (9)", "equipo": "4 DKADAS", "goles": 10},
        {"nombre": "Jonathan Osejos (19)", "equipo": "4 DKADAS", "goles": 1},
        {"nombre": "Maykel C. (17)", "equipo": "4 DKADAS", "goles": 1},
        {"nombre": "Bryan Ruano (11)", "equipo": "4 DKADAS", "goles": 1},
        {"nombre": "Yerdely A. (21)", "equipo": "4 DKADAS", "goles": 6},
        {"nombre": "Snaider Cervantes (12)", "equipo": "4 DKADAS", "goles": 2},
        {"nombre": "Juan Carlos Cuamacás (80)", "equipo": "ÁGUILAS DEL MOTILÓN", "goles": 3},
        {"nombre": "Iván Cortez (7)", "equipo": "ÁGUILAS DEL MOTILÓN", "goles": 6},
        {"nombre": "Estiven Folleco (10)", "equipo": "ÁGUILAS DEL MOTILÓN", "goles": 11},
        {"nombre": "Emerson Guapaz (15)", "equipo": "ÁGUILAS DEL MOTILÓN", "goles": 3},
        {"nombre": "Samuel Borja (12)", "equipo": "ÁGUILAS DEL MOTILÓN", "goles": 2},
        {"nombre": "Luis Aguirre (9)", "equipo": "ÁGUILAS DEL MOTILÓN", "goles": 1},
        {"nombre": "Daniel Torres (117)", "equipo": "ÁGUILAS DEL MOTILÓN", "goles": 1},
        {"nombre": "Schneider Guapaz (11)", "equipo": "ÁGUILAS DEL MOTILÓN", "goles": 2},
        {"nombre": "Alveiro Quiroz (666)", "equipo": "ÁGUILAS DEL MOTILÓN", "goles": 3},
        {"nombre": "Leandro Andino (8)", "equipo": "ÁGUILAS DEL MOTILÓN", "goles": 2},
        {"nombre": "Jimmy Valenzuela (3)", "equipo": "ÁGUILAS DEL MOTILÓN", "goles": 2},
        {"nombre": "Samid Montenegro (12)", "equipo": "ESTRELLA JUVENIL", "goles": 2},
        {"nombre": "Isaac Heredia (19)", "equipo": "ESTRELLA JUVENIL", "goles": 10},
        {"nombre": "Dennis Villota (24)", "equipo": "ESTRELLA JUVENIL", "goles": 19},
        {"nombre": "Alexander Robles (6)", "equipo": "ESTRELLA JUVENIL", "goles": 7},
        {"nombre": "Jhon Rincones (1)", "equipo": "ESTRELLA JUVENIL", "goles": 1},
        {"nombre": "David Calán (18)", "equipo": "ESTRELLA JUVENIL", "goles": 2},
        {"nombre": "Henry Becerra (27)", "equipo": "ESTRELLA JUVENIL", "goles": 1},
        {"nombre": "Hector Teran (17)", "equipo": "ESTRELLA JUVENIL", "goles": 2},
        {"nombre": "Faver Paspuel (9)", "equipo": "ESTRELLA JUVENIL", "goles": 5},
        {"nombre": "Dario Ponce (90)", "equipo": "ESTRELLA JUVENIL", "goles": 1},
        {"nombre": "Sebastian Cuical (19)", "equipo": "MILAN", "goles": 6},
        {"nombre": "Diego Nipaz (20)", "equipo": "MILAN", "goles": 3},
        {"nombre": "Alan Folleco (7)", "equipo": "MILAN", "goles": 18},
        {"nombre": "Javier Erazo (11)", "equipo": "MILAN", "goles": 1},
        {"nombre": "Luis Taramuel (16)", "equipo": "MILAN", "goles": 1},
        {"nombre": "Jeferson Guadir (15)", "equipo": "MILAN", "goles": 1},
        {"nombre": "Alexander Quelal (30)", "equipo": "MILAN", "goles": 2},
        {"nombre": "Milton A. (22)", "equipo": "MILAN", "goles": 1},
        {"nombre": "Iván Cuical (00)", "equipo": "MILAN", "goles": 8},
        {"nombre": "Gary Grefa (8)", "equipo": "C.D MONTE OLIVO", "goles": 7},
        {"nombre": "Jefferson Erazo (96)", "equipo": "C.D MONTE OLIVO", "goles": 6},
        {"nombre": "Jhon Diaz (11)", "equipo": "C.D MONTE OLIVO", "goles": 13},
        {"nombre": "Eimar Robles (9)", "equipo": "C.D MONTE OLIVO", "goles": 2},
        {"nombre": "Daniel Suarez (28)", "equipo": "C.D MONTE OLIVO", "goles": 2},
        {"nombre": "David Villota (22)", "equipo": "C.D MONTE OLIVO", "goles": 1},
        {"nombre": "Henry Villaruel (29)", "equipo": "C.D MONTE OLIVO", "goles": 29},
        {"nombre": "Jhonny Erazo (8)", "equipo": "C.D MONTE OLIVO", "goles": 1},
        {"nombre": "Adrian Inlago", "equipo": "C.D MONTE OLIVO", "goles": 1},
        {"nombre": "Eros Enriquez (25)", "equipo": "C.D MONTE OLIVO", "goles": 1},
        {"nombre": "Jair Narváez", "equipo": "C.D MONTE OLIVO", "goles": 1},
        {"nombre": "Fabricio Huera", "equipo": "C.D MONTE OLIVO", "goles": 1},
        {"nombre": "Jorge Narváez (20)", "equipo": "C.D MONTE OLIVO", "goles": 1},
        {"nombre": "Carlos Narváez (23)", "equipo": "C.D MONTE OLIVO", "goles": 1},
        {"nombre": "Santiago Coral (10)", "equipo": "C.D MONTE OLIVO", "goles": 3},
        {"nombre": "Gabino Villarruel (27)", "equipo": "C.D MONTE OLIVO", "goles": 1},
        {"nombre": "Santiago Bazurto (24)", "equipo": "C.D MONTE OLIVO", "goles": 3},
        {"nombre": "Michael De Jesús (16)", "equipo": "SOLO PANAS", "goles": 5},
        {"nombre": "Ariel Martínez (17)", "equipo": "SOLO PANAS", "goles": 1},
        {"nombre": "Jostin Folleco (19)", "equipo": "SOLO PANAS", "goles": 9},
        {"nombre": "Joel Villota (10)", "equipo": "SOLO PANAS", "goles": 7},
        {"nombre": "Jostin Sepeda (11)", "equipo": "SOLO PANAS", "goles": 10},
        {"nombre": "Cristian Sarchi (7)", "equipo": "SOLO PANAS", "goles": 4},
        {"nombre": "Antony Usuay (911)", "equipo": "SOLO PANAS", "goles": 7},
        {"nombre": "Martin Cuamacás (22)", "equipo": "SOLO PANAS", "goles": 1},
        {"nombre": "Mario Usuay (15)", "equipo": "SOLO PANAS", "goles": 1},
        {"nombre": "Elvis Mena (21)", "equipo": "SOLO PANAS", "goles": 1},
        {"nombre": "Edgar Mena (8)", "equipo": "SOLO PANAS", "goles": 1},
        {"nombre": "Schneider Paspuel (90)", "equipo": "SOLO PANAS", "goles": 2},
        {"nombre": "German Mena (4)", "equipo": "SOLO PANAS", "goles": 1},
        {"nombre": "Joshep Robles (30)", "equipo": "SOLO PANAS", "goles": 5},
        {"nombre": "Elvis Narváez (5)", "equipo": "SOLO PANAS", "goles": 3},
        {"nombre": "Weimar Pérez (12)", "equipo": "ATHLETICO SAN RAFAEL", "goles": 1},
        {"nombre": "Herman Armas (19)", "equipo": "ATHLETICO SAN RAFAEL", "goles": 21},
        {"nombre": "Harol Lopez (10)", "equipo": "ATHLETICO SAN RAFAEL", "goles": 3},
        {"nombre": "Esteban Suarez (9)", "equipo": "ATHLETICO SAN RAFAEL", "goles": 15},
        {"nombre": "Alex Castillo (18)", "equipo": "ATHLETICO SAN RAFAEL", "goles": 2},
        {"nombre": "Walter Burbano (3)", "equipo": "ATHLETICO SAN RAFAEL", "goles": 1},
        {"nombre": "Geovanny Fuelpaz (17)", "equipo": "ATHLETICO SAN RAFAEL", "goles": 1},
        {"nombre": "Brayan Quelal (51)", "equipo": "ATHLETICO SAN RAFAEL", "goles": 1},
        {"nombre": "Mateo Erazo (22)", "equipo": "ATHLETICO SAN RAFAEL", "goles": 5},
        {"nombre": "Lenin Terán (11)", "equipo": "ATHLETICO SAN RAFAEL", "goles": 3},
        {"nombre": "Said (8)", "equipo": "ATHLETICO SAN RAFAEL", "goles": 1},
        {"nombre": "Ronaldo Hidalgo (47)", "equipo": "ATHLETICO SAN RAFAEL", "goles": 2}
        
    ]
}